<?xml version="1.0" encoding="UTF-8" ?>
<!DOCTYPE mapper
  PUBLIC "-//mybatis.org//DTD Mapper 3.0//EN"
  "https://mybatis.org/dtd/mybatis-3-mapper.dtd">
<mapper namespace="com.sist.bbs_next.mapper.BbsMapper">

    
	<resultMap id="map1" type="com.sist.bbs_next.vo.BbsVO">
		<id column="b_idx" property="b_idx" />
	    <collection property="c_list" select="com.sist.bbs_next.mapper.CommMapper.commList" column="b_idx" ofType="com.sist.bbs_next.vo.CommVO" />
	</resultMap>

    <!-- 총 게시물의 수를 반환 -->
    <select id="count" parameterType="Map" resultType="int">
        SELECT COUNT(*)
        FROM `bbs_t`
        <where>
        bname = #{bname} AND status = 0
            <if test="searchType != null and searchValue != null">
                <choose>
                    <when test="searchType == 1">AND subject LIKE CONCAT('%',#{searchValue},'%')</when>
                    <when test="searchType == 2">AND writer LIKE CONCAT('%',#{searchValue},'%')</when>
                    <when test="searchType == 3">AND content LIKE CONCAT('%',#{searchValue},'%')</when>
                </choose>
            </if>
        </where>
    </select>

    <!-- 게시물 목록 반환 -->
    <select id="bbsList" parameterType="Map" resultMap="map1">
        SELECT *
        FROM (
            SELECT @RN:=@RN+1 AS rnum, a.*
            FROM (
                SELECT *
                FROM `bbs_t`
                <where>
                bname = #{bname} AND status = 0
                    <if test="searchType != null and searchValue != null">
                        <choose>
                            <when test="searchType == 1">AND subject LIKE CONCAT('%',#{searchValue},'%')</when>
                            <when test="searchType == 2">AND writer LIKE CONCAT('%',#{searchValue},'%')</when>
                            <when test="searchType == 3">AND content LIKE CONCAT('%',#{searchValue},'%')</when>
                        </choose>
                    </if>
                </where>
                ORDER BY b_idx DESC
                ) a, (SELECT @RN:=0) b
            ) c
        WHERE c.rnum BETWEEN #{begin} AND #{end}
    </select>

    
    <!-- 게시글 반환 -->
    <select id="getBbs" parameterType="Map" resultMap="map1">
        SELECT *
        FROM `bbs_t`
        WHERE b_idx = #{b_idx} AND status = 0
    </select>

    <!-- 게시글 수정 -->
    <update id="edit" parameterType="Map">
        UPDATE `bbs_t`
        SET content = #{content}
        WHERE b_idx = #{b_idx}
    </update>

    <!-- 조회수 업뎃 -->
    <update id="hit" parameterType="int">
        UPDATE `bbs_t`
        SET hit = hit+1
        WHERE b_idx = #{b_idx}
    </update>

    <!-- 게시글 저장 -->
    <insert id="add" parameterType="com.sist.bbs_next.vo.BbsVO">
        INSERT
        INTO `bbs_t`(subject, writer, content, file_name, ori_name, write_date, ip,  hit , bname, status)
        VALUES(#{subject},#{writer},#{content},#{file_name},#{ori_name},NOW(),#{ip},0,#{bname},0)
    </insert>


</mapper>